Workbook

Sheet Cover
A1: Field | B1: Input
A2: Company Name | B2: Carriage Services, Inc.
A3: Ticker | B3: CSV
A4: Industry | B4: Business Services
A5: Valuation Date | B5: 46161
A6: Current Share Price | B6: =Inputs!C2 -> 44.07
A7: Market Cap | B7: ='Multiples Check'!B3 -> 688990380
A8: Name | B8: Ellis Walker
B10: Value Per Share
A11: DCF | B11: =DCF!B18 -> 12.918058
A12: Dividend Model (Not Meaningful) | B12: ='Dividend Model'!C6 -> 5.79375
A13: Multiples Check | B13: ='Multiples Check'!D22 -> 31.597512
A15: Final Estimated Range | B15: =Conclusion!B11 -> $24.00 - $32.00
A17: Midpoint | B17: =Conclusion!D21 -> 26.927648
A18: Margin of Safety | B18: 0.15
A19: Target Entry Price | B19: =B17*(1-B18) -> 22.888501
A20: Decision | B20: =Conclusion!B15 -> Watchlist / Do Not Buy
A22: Note: The dividend model is excluded because dividends are not the primary source of shareholder value. The DCF is treated as a downside case because high leverage materially reduces equity value under conservative assumptions. The final range is based primarily on normalized earnings and EBITDA multiples, while cross-checking that the lower end remains above the more favorable DCF sensitivity cases

Sheet Inputs
A1: Input | B1: Conservative | C1: Base | D1: Optimistic
A2: Current Share Price | B2: =C2 -> 44.07 | C2: 44.07 | D2: =C2 -> 44.07
A3: Diluted Shares Outstanding | B3: =C3 -> 15634000 | C3: 15634000 | D3: =C3 -> 15634000
A4: Cash | B4: =C4 -> 1688000 | C4: 1688000 | D4: =C4 -> 1688000
A5: Total Debt | B5: =C5 -> 541970000 | C5: 541970000 | D5: =C5 -> 541970000
A6: Revenue Growth | B6: 0.02 | C6: 0.035 | D6: 0.05
A7: Operating Margin | B7: 0.19 | C7: 0.21 | D7: 0.23
A8: Tax Rate | B8: 0.27 | C8: 0.27 | D8: 0.27
A9: D&A / Revenue | B9: 0.05 | C9: ='Historical Financials'!L26 -> 0.054834094 | D9: 0.057
A10: Capex / Revenue | B10: 0.06 | C10: ='Historical Financials'!L25 -> 0.055714931 | D10: 0.05
A11: Change in NWC / Revenue | B11: 0.01 | C11: 0.005 | D11: 0
A12: Discount Rate | B12: 0.12 | C12: 0.11 | D12: 0.1
A13: Terminal Growth Rate | B13: 0.015 | C13: 0.02 | D13: 0.025
A14: Dividend Growth Rate | B14: 0.02 | C14: 0.03 | D14: 0.04
A15: Required Return for Dividend Model | B15: 0.12 | C15: 0.11 | D15: 0.1

Sheet Historical Financials
B1: 2016 | C1: 2017 | D1: 2018 | E1: 2019 | F1: 2020 | G1: 2021 | H1: 2022 | I1: 2023 | J1: 2024 | K1: 2025 | L1: Average
A2: Revenue | B2: 248200000 | C2: 258139000 | D2: 267992000 | E2: 274107000 | F2: 329448000 | G2: 375886000 | H2: 370174000 | I2: 382520000 | J2: 404198000 | K2: 417440000 | L2: =IFERROR(__xludf.DUMMYFUNCTION("IFERROR(AVERAGE(FILTER(B2:K2,B2:K2<>"""")),"""")"),3.328104E8) -> 332810400
A3: Revenue Growth | C3: =IFERROR(C2/B2-1,"") -> 0.040044319 | D3: =IFERROR(D2/C2-1,"") -> 0.038169358 | E3: =IFERROR(E2/D2-1,"") -> 0.022817845 | F3: =IFERROR(F2/E2-1,"") -> 0.20189561 | G3: =IFERROR(G2/F2-1,"") -> 0.14095699 | H3: =IFERROR(H2/G2-1,"") -> -0.015196097 | I3: =IFERROR(I2/H2-1,"") -> 0.033351883 | J3: =IFERROR(J2/I2-1,"") -> 0.056671547 | K3: =IFERROR(K2/J2-1,"") -> 0.032761172 | L3: =IFERROR(__xludf.DUMMYFUNCTION("IFERROR(AVERAGE(FILTER(C3:K3,C3:K3<>"""")),"""")"),0.061274736909413194) -> 0.061274737
A4: Operating Income | B4: 50204000 | C4: 48941000 | D4: 43307000 | E4: 52289000 | F4: 57227000 | G4: 93660000 | H4: 79726000 | I4: 80979000 | J4: 81799000 | K4: 97657000 | L4: =IFERROR(__xludf.DUMMYFUNCTION("IFERROR(AVERAGE(FILTER(B4:K4,B4:K4<>"""")),"""")"),6.85789E7) -> 68578900
A5: Operating Margin | B5: =IFERROR(B4/B2,"") -> 0.20227236 | C5: =IFERROR(C4/C2,"") -> 0.18959165 | D5: =IFERROR(D4/D2,"") -> 0.16159811 | E5: =IFERROR(E4/E2,"") -> 0.19076127 | F5: =IFERROR(F4/F2,"") -> 0.17370571 | G5: =IFERROR(G4/G2,"") -> 0.24917129 | H5: =IFERROR(H4/H2,"") -> 0.21537439 | I5: =IFERROR(I4/I2,"") -> 0.21169873 | ... K5: =IFERROR(K4/K2,"") -> 0.2339426 | L5: =IFERROR(__xludf.DUMMYFUNCTION("IFERROR(AVERAGE(FILTER(B5:K5,B5:K5<>"""")),"""")"),0.203048971758833) -> 0.20304897
A6: Income Before Tax | B6: 32241000 | C6: 32782000 | D6: 18266000 | E6: 22416000 | F6: 24642000 | G6: 44304000 | H6: 57194000 | I6: 46429000 | J6: 50080000 | K6: 70263000 | L6: =IFERROR(__xludf.DUMMYFUNCTION("IFERROR(AVERAGE(FILTER(B6:K6,B6:K6<>"""")),"""")"),3.98617E7) -> 39861700
A7: Tax Expense | B7: 12660000 | C7: -4411000 | D7: 5754000 | E7: 7395000 | F7: 8552000 | G7: 11145000 | H7: 15813000 | I7: 13016000 | J7: 17127000 | K7: 18756000 | L7: =IFERROR(__xludf.DUMMYFUNCTION("IFERROR(AVERAGE(FILTER(B7:K7,B7:K7<>"""")),"""")"),1.05807E7) -> 10580700
A8: Tax Rate | B8: =IFERROR(B7/B6,"") -> 0.39266772 | C8: =IFERROR(C7/C6,"") -> -0.13455555 | D8: =IFERROR(D7/D6,"") -> 0.3150115 | E8: =IFERROR(E7/E6,"") -> 0.32989829 | F8: =IFERROR(F7/F6,"") -> 0.34704975 | G8: =IFERROR(G7/G6,"") -> 0.25155742 | H8: =IFERROR(H7/H6,"") -> 0.27648005 | I8: =IFERROR(I7/I6,"") -> 0.28034203 | ... K8: =IFERROR(K7/K6,"") -> 0.26693993 | L8: =IFERROR(__xludf.DUMMYFUNCTION("IFERROR(AVERAGE(FILTER(B8:K8,B8:K8<>"""")),"""")"),0.26673839452388426) -> 0.26673839
A9: Net Income | B9: 19581000 | C9: 37193000 | D9: 11645000 | E9: 14533000 | F9: 16090000 | G9: 33159000 | H9: 41381000 | I9: 33413000 | J9: 32953000 | K9: 51507000 | L9: =IFERROR(__xludf.DUMMYFUNCTION("IFERROR(AVERAGE(FILTER(B9:K9,B9:K9<>"""")),"""")"),2.91455E7) -> 29145500
A10: Net Margin | B10: =IFERROR(B9/B2,"") -> 0.078892023 | C10: =IFERROR(C9/C2,"") -> 0.14408129 | D10: =IFERROR(D9/D2,"") -> 0.04345279 | E10: =IFERROR(E9/E2,"") -> 0.053019441 | F10: =IFERROR(F9/F2,"") -> 0.048839271 | G10: =IFERROR(G9/G2,"") -> 0.088215576 | H10: =IFERROR(H9/H2,"") -> 0.11178797 | I10: =IFERROR(I9/I2,"") -> 0.087349681 | ... K10: =IFERROR(K9/K2,"") -> 0.12338779 | L10: =IFERROR(__xludf.DUMMYFUNCTION("IFERROR(AVERAGE(FILTER(B10:K10,B10:K10<>"""")),"""")"),0.08605527083292382) -> 0.086055271
A11: D&A | B11: 13919000 | C11: 14374000 | D11: 15617000 | E11: 16355000 | F11: 17962000 | G11: 19279000 | H11: 19175000 | I11: 20205000 | J11: 21897000 | K11: 22555000 | L11: =IFERROR(__xludf.DUMMYFUNCTION("IFERROR(AVERAGE(FILTER(B11:K11,B11:K11<>"""")),"""")"),1.81338E7) -> 18133800
A12: Operating Cash Flow | B12: 50035000 | C12: 45230000 | D12: 48994000 | E12: 43216000 | F12: 82915000 | G12: 84246000 | H12: 61024000 | I12: 75590000 | J12: 51996000 | K12: 60693000 | L12: =IFERROR(__xludf.DUMMYFUNCTION("IFERROR(AVERAGE(FILTER(B12:K12,B12:K12<>"""")),"""")"),6.03939E7) -> 60393900
A13: Capital Expenditures | B13: 16846000 | C13: 16395000 | D13: 13526000 | E13: 15379000 | F13: 15198000 | G13: 24883000 | H13: 26081000 | I13: 18039000 | J13: 16098000 | K13: 20628000 | L13: =IFERROR(__xludf.DUMMYFUNCTION("IFERROR(AVERAGE(FILTER(B13:K13,B13:K13<>"""")),"""")"),1.83073E7) -> 18307300
A14: Free Cash Flow | B14: =IFERROR(B12-B13,"") -> 33189000 | C14: =IFERROR(C12-C13,"") -> 28835000 | D14: =IFERROR(D12-D13,"") -> 35468000 | E14: =IFERROR(E12-E13,"") -> 27837000 | F14: =IFERROR(F12-F13,"") -> 67717000 | G14: =IFERROR(G12-G13,"") -> 59363000 | H14: =IFERROR(H12-H13,"") -> 34943000 | I14: =IFERROR(I12-I13,"") -> 57551000 | ... K14: =IFERROR(K12-K13,"") -> 40065000 | L14: =IFERROR(__xludf.DUMMYFUNCTION("IFERROR(AVERAGE(FILTER(B14:K14,B14:K14<>"""")),"""")"),4.20866E7) -> 42086600
A15: Cash | B15: 3286000 | C15: 952000 | D15: 644000 | E15: 716000 | F15: 889000 | G15: 1148000 | H15: 1170000 | I15: 15823000 | J15: 1165000 | K15: 1688000 | L15: =IFERROR(__xludf.DUMMYFUNCTION("IFERROR(AVERAGE(FILTER(B15:K15,B15:K15<>"""")),"""")"),2748100.0) -> 2748100
A16: Total Debt | B16: 337267000 | C16: 353846000 | D16: 366380000 | E16: 490854000 | F16: 458015000 | G16: 560412000 | H16: 595432000 | I16: 588833000 | J16: 546833000 | K16: 541970000 | L16: =IFERROR(__xludf.DUMMYFUNCTION("IFERROR(AVERAGE(FILTER(B16:K16,B16:K16<>"""")),"""")"),4.839842E8) -> 483984200
A17: Shareholders’ Equity | B17: 175734000 | C17: 197656000 | D17: 221492000 | E17: 226569000 | F17: 240502000 | G17: 128015000 | H17: 137134000 | I17: 173060000 | J17: 208550000 | K17: 254776000 | L17: =IFERROR(__xludf.DUMMYFUNCTION("IFERROR(AVERAGE(FILTER(B17:K17,B17:K17<>"""")),"""")"),1.963488E8) -> 196348800
A18: Invested Capital | B18: =IFERROR(B16+B17-B15,"") -> 509715000 | C18: =IFERROR(C16+C17-C15,"") -> 550550000 | D18: =IFERROR(D16+D17-D15,"") -> 587228000 | E18: =IFERROR(E16+E17-E15,"") -> 716707000 | F18: =IFERROR(F16+F17-F15,"") -> 697628000 | G18: =IFERROR(G16+G17-G15,"") -> 687279000 | H18: =IFERROR(H16+H17-H15,"") -> 731396000 | I18: =IFERROR(I16+I17-I15,"") -> 746070000 | ... K18: =IFERROR(K16+K17-K15,"") -> 795058000 | L18: =IFERROR(__xludf.DUMMYFUNCTION("IFERROR(AVERAGE(FILTER(B18:K18,B18:K18<>"""")),"""")"),6.775849E8) -> 677584900
A19: Shares Outstanding | B19: 17460000 | C19: 17715000 | D19: 18374000 | E19: 18005000 | F19: 18077000 | G19: 18266000 | H19: 15710000 | I19: 15455000 | J19: 15443000 | K19: 15634000 | L19: =IFERROR(__xludf.DUMMYFUNCTION("IFERROR(AVERAGE(FILTER(B19:K19,B19:K19<>"""")),"""")"),1.70139E7) -> 17013900
A20: Dividend Per Share | B20: 0.15 | C20: 0.225 | D20: 0.3 | E20: 0.3 | F20: 0.3375 | G20: 0.4125 | H20: 0.45 | I20: 0.45 | J20: 0.45 | K20: 0.45 | L20: =IFERROR(__xludf.DUMMYFUNCTION("IFERROR(AVERAGE(FILTER(B20:K20,B20:K20<>"""")),"""")"),0.3525000000000001) -> 0.3525
A21: Dividends Paid | B21: =IFERROR(B20*B19,"") -> 2619000 | C21: =IFERROR(C20*C19,"") -> 3985875 | D21: =IFERROR(D20*D19,"") -> 5512200 | E21: =IFERROR(E20*E19,"") -> 5401500 | F21: =IFERROR(F20*F19,"") -> 6100987.5 | G21: =IFERROR(G20*G19,"") -> 7534725 | H21: =IFERROR(H20*H19,"") -> 7069500 | I21: =IFERROR(I20*I19,"") -> 6954750 | ... K21: =IFERROR(K20*K19,"") -> 7035300 | L21: =IFERROR(__xludf.DUMMYFUNCTION("IFERROR(AVERAGE(FILTER(B21:K21,B21:K21<>"""")),"""")"),5916318.75) -> 5916318.8
A22: NOPAT | B22: =B4*(1-B8) -> 30490510 | C22: =C4*(1-C8) -> 55526283 | D22: =D4*(1-D8) -> 29664797 | E22: =E4*(1-E8) -> 35038948 | F22: =F4*(1-F8) -> 37366384 | G22: =G4*(1-G8) -> 70099132 | H22: =H4*(1-H8) -> 57683352 | I22: =I4*(1-I8) -> 58277183 | ... K22: =K4*(1-K8) -> 71588448 | L22: =IFERROR(__xludf.DUMMYFUNCTION("IFERROR(AVERAGE(FILTER(B22:K22,B22:K22<>"""")),"""")"),4.9955936628163986E7) -> 49955937
A23: ROIC | B23: =IFERROR(B22/B18,"") -> 0.059818741 | C23: =IFERROR(C22/C18,"") -> 0.10085602 | D23: =IFERROR(D22/D18,"") -> 0.05051666 | E23: =IFERROR(E22/E18,"") -> 0.048888805 | F23: =IFERROR(F22/F18,"") -> 0.053562047 | G23: =IFERROR(G22/G18,"") -> 0.10199516 | H23: =IFERROR(H22/H18,"") -> 0.078867469 | I23: =IFERROR(I22/I18,"") -> 0.078112219 | ... K23: =IFERROR(K22/K18,"") -> 0.090041793 | L23: =IFERROR(__xludf.DUMMYFUNCTION("IFERROR(AVERAGE(FILTER(B23:K23,B23:K23<>"""")),"""")"),0.07340233361429863) -> 0.073402334
A24: Debt / Equity | B24: =IFERROR(B16/B17,0) -> 1.9191904 | C24: =IFERROR(C16/C17,0) -> 1.7902113 | D24: =IFERROR(D16/D17,0) -> 1.6541455 | E24: =IFERROR(E16/E17,0) -> 2.1664658 | F24: =IFERROR(F16/F17,0) -> 1.9044124 | G24: =IFERROR(G16/G17,0) -> 4.3777057 | H24: =IFERROR(H16/H17,0) -> 4.3419721 | I24: =IFERROR(I16/I17,0) -> 3.4024789 | ... K24: =IFERROR(K16/K17,0) -> 2.1272412 | L24: =IFERROR(__xludf.DUMMYFUNCTION("IFERROR(AVERAGE(FILTER(B24:K24,B24:K24<>"""")),"""")"),2.6305894810227053) -> 2.6305895
A25: Capex / Revenue | B25: =IFERROR(B13/B2,0) -> 0.067872683 | C25: =IFERROR(C13/C2,0) -> 0.063512294 | D25: =IFERROR(D13/D2,0) -> 0.050471656 | E25: =IFERROR(E13/E2,0) -> 0.056105827 | F25: =IFERROR(F13/F2,0) -> 0.046131711 | G25: =IFERROR(G13/G2,0) -> 0.066198262 | H25: =IFERROR(H13/H2,0) -> 0.070456056 | I25: =IFERROR(I13/I2,0) -> 0.047158319 | ... K25: =IFERROR(K13/K2,0) -> 0.049415485 | L25: =IFERROR(__xludf.DUMMYFUNCTION("IFERROR(AVERAGE(FILTER(B25:K25,B25:K25<>"""")),"""")"),0.05571493083587918) -> 0.055714931
A26: D&A / Revenue | B26: =IFERROR(B11/B2,0) -> 0.056079774 | C26: =IFERROR(C11/C2,0) -> 0.055683178 | D26: =IFERROR(D11/D2,0) -> 0.058274128 | E26: =IFERROR(E11/E2,0) -> 0.059666481 | F26: =IFERROR(F11/F2,0) -> 0.054521503 | G26: =IFERROR(G11/G2,0) -> 0.051289487 | H26: =IFERROR(H11/H2,0) -> 0.051799964 | I26: =IFERROR(I11/I2,0) -> 0.052820768 | ... K26: =IFERROR(K11/K2,0) -> 0.054031717 | L26: =IFERROR(__xludf.DUMMYFUNCTION("IFERROR(AVERAGE(FILTER(B26:K26,B26:K26<>"""")),"""")"),0.05483409438213749) -> 0.054834094
A27: FCF / Revenue | B27: =IFERROR(B14/B2,0) -> 0.13371878 | C27: =IFERROR(C14/C2,0) -> 0.11170338 | D27: =IFERROR(D14/D2,0) -> 0.13234723 | E27: =IFERROR(E14/E2,0) -> 0.10155523 | F27: =IFERROR(F14/F2,0) -> 0.20554685 | G27: =IFERROR(G14/G2,0) -> 0.1579282 | H27: =IFERROR(H14/H2,0) -> 0.094396149 | I27: =IFERROR(I14/I2,0) -> 0.15045226 | ... K27: =IFERROR(K14/K2,0) -> 0.095977865 | L27: =IFERROR(__xludf.DUMMYFUNCTION("IFERROR(AVERAGE(FILTER(B27:K27,B27:K27<>"""")),"""")"),0.1272438868265448) -> 0.12724389
A28: Dividend Payout Ratio | B28: =IFERROR(B21/B9,0) -> 0.13375211 | C28: =IFERROR(C21/C9,0) -> 0.10716734 | D28: =IFERROR(D21/D9,0) -> 0.47335337 | E28: =IFERROR(E21/E9,0) -> 0.37167137 | F28: =IFERROR(F21/F9,0) -> 0.37917884 | G28: =IFERROR(G21/G9,0) -> 0.22723016 | H28: =IFERROR(H21/H9,0) -> 0.17083927 | I28: =IFERROR(I21/I9,0) -> 0.20814503 | ... K28: =IFERROR(K21/K9,0) -> 0.1365892 | L28: =IFERROR(__xludf.DUMMYFUNCTION("IFERROR(AVERAGE(FILTER(B28:K28,B28:K28<>"""")),"""")"),0.24188134169968772) -> 0.24188134
A29: Book Value Per Share | B29: =IFERROR(B17/B19,0) -> 10.064948 | C29: =IFERROR(C17/C19,0) -> 11.15755 | D29: =IFERROR(D17/D19,0) -> 12.054642 | E29: =IFERROR(E17/E19,0) -> 12.583671 | F29: =IFERROR(F17/F19,0) -> 13.304309 | G29: =IFERROR(G17/G19,0) -> 7.0083762 | H29: =IFERROR(H17/H19,0) -> 8.7290898 | I29: =IFERROR(I17/I19,0) -> 11.197671 | ... K29: =IFERROR(K17/K19,0) -> 16.296277 | L29: =IFERROR(__xludf.DUMMYFUNCTION("IFERROR(AVERAGE(FILTER(B29:K29,B29:K29<>"""")),"""")"),11.590103591948123) -> 11.590104
A31: Note: D&A = cemetery property amortization + field depreciation expense

Sheet Forecast
B1: 2025A | C1: 2026E | D1: 2027E | E1: 2028E | F1: 2029E | G1: 2030E
A2: Revenue | B2: ='Historical Financials'!K2 -> 417440000 | C2: =B2*(1+Inputs!$C$6) -> 432050400 | D2: =C2*(1+Inputs!$C$6) -> 447172164 | E2: =D2*(1+Inputs!$C$6) -> 4.6282319e+08 | F2: =E2*(1+Inputs!$C$6) -> 4.79022e+08 | G2: =F2*(1+Inputs!$C$6) -> 4.9578777e+08
A3: Revenue Growth | B3: ='Historical Financials'!K3 -> 0.032761172 | C3: =Inputs!$C$6 -> 0.035 | D3: =Inputs!$C$6 -> 0.035 | E3: =Inputs!$C$6 -> 0.035 | F3: =Inputs!$C$6 -> 0.035 | G3: =Inputs!$C$6 -> 0.035
A4: Operating Income | B4: ='Historical Financials'!K4 -> 97657000 | C4: =C2*C5 -> 90730584 | D4: =D2*D5 -> 93906154 | E4: =E2*E5 -> 97192870 | F4: =F2*F5 -> 1.0059462e+08 | G4: =G2*G5 -> 104115432
A5: Operating Margin | B5: ='Historical Financials'!K5 -> 0.2339426 | C5: =Inputs!$C$7 -> 0.21 | D5: =Inputs!$C$7 -> 0.21 | E5: =Inputs!$C$7 -> 0.21 | F5: =Inputs!$C$7 -> 0.21 | G5: =Inputs!$C$7 -> 0.21
A6: Tax Rate | B6: ='Historical Financials'!K8 -> 0.26693993 | C6: =Inputs!$C$8 -> 0.27 | D6: =Inputs!$C$8 -> 0.27 | E6: =Inputs!$C$8 -> 0.27 | F6: =Inputs!$C$8 -> 0.27 | G6: =Inputs!$C$8 -> 0.27
A7: NOPAT | B7: ='Historical Financials'!K22 -> 71588448 | C7: =C4*(1-C6) -> 66233326 | D7: =D4*(1-D6) -> 68551493 | E7: =E4*(1-E6) -> 70950795 | F7: =F4*(1-F6) -> 73434073 | G7: =G4*(1-G6) -> 76004265
A8: D&A | B8: ='Historical Financials'!K11 -> 22555000 | C8: =C2*C9 -> 23691092 | D8: =D2*D9 -> 24520281 | E8: =E2*E9 -> 25378490 | F8: =F2*F9 -> 26266738 | G8: =G2*G9 -> 27186073
A9: D&A / Revenue | B9: ='Historical Financials'!K26 -> 0.054031717 | C9: =Inputs!$C$9 -> 0.054834094 | D9: =Inputs!$C$9 -> 0.054834094 | E9: =Inputs!$C$9 -> 0.054834094 | F9: =Inputs!$C$9 -> 0.054834094 | G9: =Inputs!$C$9 -> 0.054834094
A10: Capital Expenditures | B10: ='Historical Financials'!K13 -> 20628000 | C10: =C2*C11 -> 24071658 | D10: =D2*D11 -> 24914166 | E10: =E2*E11 -> 25786162 | F10: =F2*F11 -> 26688678 | G10: =G2*G11 -> 27622781
A11: Capex / Revenue | B11: ='Historical Financials'!K25 -> 0.049415485 | C11: =Inputs!$C$10 -> 0.055714931 | D11: =Inputs!$C$10 -> 0.055714931 | E11: =Inputs!$C$10 -> 0.055714931 | F11: =Inputs!$C$10 -> 0.055714931 | G11: =Inputs!$C$10 -> 0.055714931
A12: Change in NWC | B12: =0 -> 0 | C12: =C2*Inputs!$C$11 -> 2160252 | D12: =D2*Inputs!$C$11 -> 2235860.8 | E12: =E2*Inputs!$C$11 -> 2314115.9 | F12: =F2*Inputs!$C$11 -> 2395110 | G12: =G2*Inputs!$C$11 -> 2478938.9
A13: Unlevered Free Cash Flow | B13: =IFERROR(B7+B8-B10-B12,"") -> 73515448 | C13: =C7+C8-C10-C12 -> 63692509 | D13: =D7+D8-D10-D12 -> 65921746 | E13: =E7+E8-E10-E12 -> 68229008 | F13: =F7+F8-F10-F12 -> 70617023 | G13: =G7+G8-G10-G12 -> 73088619
A14: Net Income | B14: ='Historical Financials'!K9 -> 51507000 | C14: =C7 -> 66233326 | D14: =D7 -> 68551493 | E14: =E7 -> 70950795 | F14: =F7 -> 73434073 | G14: =G7 -> 76004265
A15: Dividends Paid | B15: ='Historical Financials'!K21 -> 7035300 | C15: =C17*C16 -> 7246359 | D15: =D17*D16 -> 7463749.8 | E15: =E17*E16 -> 7687662.3 | F15: =F17*F16 -> 7918292.1 | G15: =G17*G16 -> 8155840.9
A16: Shares Outstanding | B16: ='Historical Financials'!K19 -> 15634000 | C16: =B16 -> 15634000 | D16: =C16 -> 15634000 | E16: =D16 -> 15634000 | F16: =E16 -> 15634000 | G16: =F16 -> 15634000
A17: Dividend Per Share | B17: ='Historical Financials'!K20 -> 0.45 | C17: =B17*(1+Inputs!$C$14) -> 0.4635 | D17: =C17*(1+Inputs!$C$14) -> 0.477405 | E17: =D17*(1+Inputs!$C$14) -> 0.49172715 | F17: =E17*(1+Inputs!$C$14) -> 0.50647896 | G17: =F17*(1+Inputs!$C$14) -> 0.52167333

Sheet DCF
B1: 2026E | C1: 2027E | D1: 2028E | E1: 2029E | F1: 2030E
A2: Unlevered Free Cash Flow | B2: =Forecast!C13 -> 63692509 | C2: =Forecast!D13 -> 65921746 | D2: =Forecast!E13 -> 68229008 | E2: =Forecast!F13 -> 70617023 | F2: =Forecast!G13 -> 73088619
A3: Discount Period | B3: 1 | C3: 2 | D3: 3 | E3: 4 | F3: 5
A4: Discount Factor | B4: =1/(1+Inputs!$C$12)^B3 -> 0.9009009 | C4: =1/(1+Inputs!$C$12)^C3 -> 0.81162243 | D4: =1/(1+Inputs!$C$12)^D3 -> 0.73119138 | E4: =1/(1+Inputs!$C$12)^E3 -> 0.65873097 | F4: =1/(1+Inputs!$C$12)^F3 -> 0.59345133
A5: PV of FCF | B5: =B2*B4 -> 57380638 | C5: =C2*C4 -> 53503568 | D5: =D2*D4 -> 49888462 | E5: =E2*E4 -> 46517620 | F5: =F2*F4 -> 43374538
A7: Item | B7: Value
A8: Final Year FCF | B8: =Forecast!G13 -> 73088619
A9: Terminal Growth Rate | B9: =Inputs!C13 -> 0.02
A10: Discount Rate | B10: =Inputs!C12 -> 0.11
A11: Terminal Value | B11: =B8*(1+B9)/(B10-B9) -> 828337677
A12: PV of Terminal Value | B12: =B11/(1+B10)^5 -> 4.9157809e+08
A13: Enterprise Value | B13: =SUM(B5:F5)+B12 -> 7.4224292e+08
A14: Less: Total Debt | B14: =Inputs!C5 -> 541970000
A15: Plus: Cash | B15: =Inputs!C4 -> 1688000
A16: Equity Value | B16: =B13-B14+B15 -> 2.0196092e+08
A17: Diluted Shares | B17: =Inputs!C3 -> 15634000
A18: Intrinsic Value Per Share | B18: =B16/B17 -> 12.918058
A20: Debt Paydown Sensitivity
A21: Beginning Debt | B21: =Inputs!C5 -> 541970000 | C21: =B26 -> 5.2785846e+08 | D21: =C26 -> 5.1324396e+08 | E21: =D26 -> 4.9810863e+08 | F21: =E26 -> 4.8243394e+08
A22: Free Cash Flow | B22: =Forecast!C13 -> 63692509 | C22: =Forecast!D13 -> 65921746 | D22: =Forecast!E13 -> 68229008 | E22: =Forecast!F13 -> 70617023 | F22: =Forecast!G13 -> 73088619
A23: Dividends Paid | B23: =Forecast!C15 -> 7246359 | C23: =Forecast!D15 -> 7463749.8 | D23: =Forecast!E15 -> 7687662.3 | E23: =Forecast!F15 -> 7918292.1 | F23: =Forecast!G15 -> 8155840.9
A24: Cash Available for Debt Paydown | B24: =MAX(0,B22-B23) -> 56446150 | C24: =MAX(0,C22-C23) -> 58457997 | D24: =MAX(0,D22-D23) -> 60541345 | E24: =MAX(0,E22-E23) -> 62698731 | F24: =MAX(0,F22-F23) -> 64932778
A25: Debt Paydown | B25: =MIN(B21,B24*$B$29) -> 14111537 | C25: =MIN(C21,C24*$B$29) -> 14614499 | D25: =MIN(D21,D24*$B$29) -> 15135336 | E25: =MIN(E21,E24*$B$29) -> 15674683 | F25: =MIN(F21,F24*$B$29) -> 16233194
A26: Ending Debt | B26: =B21-B25 -> 5.2785846e+08 | C26: =C21-C25 -> 5.1324396e+08 | D26: =D21-D25 -> 4.9810863e+08 | E26: =E21-E25 -> 4.8243394e+08 | F26: =F21-F25 -> 4.6620075e+08
A27: Net Debt / EBITDA | B27: =B26/(Forecast!C4+Forecast!C8) -> 4.6132733 | C27: =C26/(Forecast!D4+Forecast!D8) -> 4.3338632 | D27: =D26/(Forecast!E4+Forecast!E8) -> 4.0638256 | E27: =E26/(Forecast!F4+Forecast!F8) -> 3.8028439 | F27: =F26/(Forecast!G4+Forecast!G8) -> 3.5506124
A29: % of Excess FCF Used for Debt Paydown | B29: 0.25
A30: Standard DCF Value | B30: =B18 -> 12.918058
A31: Deleveraging DCF Value | B31: =(B13-F26+Inputs!C4)/Inputs!C3 -> 17.764499

Sheet Dividend Model
A1: Input | B1: Conservative | C1: Base | D1: Optimistic
A2: Current Dividend Per Share | B2: =Forecast!$B$17 -> 0.45 | C2: =Forecast!$B$17 -> 0.45 | D2: =Forecast!$B$17 -> 0.45
A3: Dividend Growth Rate | B3: =Inputs!B14 -> 0.02 | C3: =Inputs!C14 -> 0.03 | D3: =Inputs!D14 -> 0.04
A4: Required Return | B4: =Inputs!B15 -> 0.12 | C4: =Inputs!C15 -> 0.11 | D4: =Inputs!D15 -> 0.1
A5: Next Year Dividend | B5: =B2*(1+B3) -> 0.459 | C5: =C2*(1+C3) -> 0.4635 | D5: =D2*(1+D3) -> 0.468
A6: Implied Value Per Share | B6: =IFERROR(B5/(B4-B3),"") -> 4.59 | C6: =IFERROR(C5/(C4-C3),"") -> 5.79375 | D6: =IFERROR(D5/(D4-D3),"") -> 7.8
A8: Note: Dividend model is not a primary valuation method for CSV because the dividend yield and payout ratio are low. This model only values the current dividend stream, not total owner earnings.

Sheet Multiples Check
A1: Metric | B1: Current
A2: Share Price | B2: =Inputs!C2 -> 44.07
A3: Market Cap | B3: =B2*Inputs!C3 -> 688990380
A4: Enterprise Value | B4: =B3+Inputs!C5-Inputs!C4 -> 1229272380
A5: Revenue | B5: =Forecast!B2 -> 417440000
A6: EBITDA | B6: =Forecast!B4+Forecast!B8 -> 120212000
A7: Net Income | B7: =Forecast!B14 -> 51507000
A8: Book Value | B8: ='Historical Financials'!K17 -> 254776000
A9: EV / Revenue | B9: =IFERROR(B4/B5,"") -> 2.9447882
A10: EV / EBITDA | B10: =IFERROR(B4/B6,"") -> 10.225871
A11: P / E | B11: =IFERROR(B3/B7,"") -> 13.376636
A12: P / Book | B12: =IFERROR(B3/B8,"") -> 2.7042986
A13: Dividend Yield | B13: =IFERROR(Forecast!B17/B2,"") -> 0.010211028
B15: Current | C15: Conservative | D15: Base | E15: Optimistic
A16: EV/EBITDA | B16: 10.23 | C16: 7 | D16: 8 | E16: 10
A17: P/E | B17: 13.38 | C17: 9 | D17: 11 | E17: 13
A19: EV/EBITDA | C19: =(($B$6*C16)-Inputs!$C$5+Inputs!$C$4)/Inputs!$C$3 -> 19.265831 | D19: =(($B$6*D16)-Inputs!$C$5+Inputs!$C$4)/Inputs!$C$3 -> 26.95497 | E19: =(($B$6*E16)-Inputs!$C$5+Inputs!$C$4)/Inputs!$C$3 -> 42.333248
A20: P/E | C20: =C17*($B$7/Inputs!$C$3) -> 29.650953 | D20: =D17*($B$7/Inputs!$C$3) -> 36.240054 | E20: =E17*($B$7/Inputs!$C$3) -> 42.829154
A22: Multiples Range | C22: =MIN(C19:C20) -> 19.265831 | D22: =AVERAGE(D19:D20) -> 31.597512 | E22: =MAX(E19:E20) -> 42.829154

Sheet Sensitivity
B1: 0.015 | C1: 0.02 | D1: 0.025 | E1: 0.03
A2: 0.1 | B2: =IFERROR((SUMPRODUCT(DCF!$B$2:$F$2,1/(1+$A2)^DCF!$B$3:$F$3)+((DCF!$B$8*(1+B$1)/($A2-B$1))/(1+$A2)^5)-Inputs!$C$5+Inputs!$C$4)/Inputs!$C$3,"") -> 16.559743 | C2: =IFERROR((SUMPRODUCT(DCF!$B$2:$F$2,1/(1+$A2)^DCF!$B$3:$F$3)+((DCF!$B$8*(1+C$1)/($A2-C$1))/(1+$A2)^5)-Inputs!$C$5+Inputs!$C$4)/Inputs!$C$3,"") -> 18.907591 | D2: =IFERROR((SUMPRODUCT(DCF!$B$2:$F$2,1/(1+$A2)^DCF!$B$3:$F$3)+((DCF!$B$8*(1+D$1)/($A2-D$1))/(1+$A2)^5)-Inputs!$C$5+Inputs!$C$4)/Inputs!$C$3,"") -> 21.568485 | E2: =IFERROR((SUMPRODUCT(DCF!$B$2:$F$2,1/(1+$A2)^DCF!$B$3:$F$3)+((DCF!$B$8*(1+E$1)/($A2-E$1))/(1+$A2)^5)-Inputs!$C$5+Inputs!$C$4)/Inputs!$C$3,"") -> 24.609508
A3: 0.105 | B3: =IFERROR((SUMPRODUCT(DCF!$B$2:$F$2,1/(1+$A3)^DCF!$B$3:$F$3)+((DCF!$B$8*(1+B$1)/($A3-B$1))/(1+$A3)^5)-Inputs!$C$5+Inputs!$C$4)/Inputs!$C$3,"") -> 13.686973 | C3: =IFERROR((SUMPRODUCT(DCF!$B$2:$F$2,1/(1+$A3)^DCF!$B$3:$F$3)+((DCF!$B$8*(1+C$1)/($A3-C$1))/(1+$A3)^5)-Inputs!$C$5+Inputs!$C$4)/Inputs!$C$3,"") -> 15.736431 | D3: =IFERROR((SUMPRODUCT(DCF!$B$2:$F$2,1/(1+$A3)^DCF!$B$3:$F$3)+((DCF!$B$8*(1+D$1)/($A3-D$1))/(1+$A3)^5)-Inputs!$C$5+Inputs!$C$4)/Inputs!$C$3,"") -> 18.042072 | E3: =IFERROR((SUMPRODUCT(DCF!$B$2:$F$2,1/(1+$A3)^DCF!$B$3:$F$3)+((DCF!$B$8*(1+E$1)/($A3-E$1))/(1+$A3)^5)-Inputs!$C$5+Inputs!$C$4)/Inputs!$C$3,"") -> 20.655132
A4: 0.11 | B4: =IFERROR((SUMPRODUCT(DCF!$B$2:$F$2,1/(1+$A4)^DCF!$B$3:$F$3)+((DCF!$B$8*(1+B$1)/($A4-B$1))/(1+$A4)^5)-Inputs!$C$5+Inputs!$C$4)/Inputs!$C$3,"") -> 11.11715 | C4: =IFERROR((SUMPRODUCT(DCF!$B$2:$F$2,1/(1+$A4)^DCF!$B$3:$F$3)+((DCF!$B$8*(1+C$1)/($A4-C$1))/(1+$A4)^5)-Inputs!$C$5+Inputs!$C$4)/Inputs!$C$3,"") -> 12.918058 | D4: =IFERROR((SUMPRODUCT(DCF!$B$2:$F$2,1/(1+$A4)^DCF!$B$3:$F$3)+((DCF!$B$8*(1+D$1)/($A4-D$1))/(1+$A4)^5)-Inputs!$C$5+Inputs!$C$4)/Inputs!$C$3,"") -> 14.930838 | E4: =IFERROR((SUMPRODUCT(DCF!$B$2:$F$2,1/(1+$A4)^DCF!$B$3:$F$3)+((DCF!$B$8*(1+E$1)/($A4-E$1))/(1+$A4)^5)-Inputs!$C$5+Inputs!$C$4)/Inputs!$C$3,"") -> 17.195216
A5: 0.115 | B5: =IFERROR((SUMPRODUCT(DCF!$B$2:$F$2,1/(1+$A5)^DCF!$B$3:$F$3)+((DCF!$B$8*(1+B$1)/($A5-B$1))/(1+$A5)^5)-Inputs!$C$5+Inputs!$C$4)/Inputs!$C$3,"") -> 8.8048188 | C5: =IFERROR((SUMPRODUCT(DCF!$B$2:$F$2,1/(1+$A5)^DCF!$B$3:$F$3)+((DCF!$B$8*(1+C$1)/($A5-C$1))/(1+$A5)^5)-Inputs!$C$5+Inputs!$C$4)/Inputs!$C$3,"") -> 10.396758 | D5: =IFERROR((SUMPRODUCT(DCF!$B$2:$F$2,1/(1+$A5)^DCF!$B$3:$F$3)+((DCF!$B$8*(1+D$1)/($A5-D$1))/(1+$A5)^5)-Inputs!$C$5+Inputs!$C$4)/Inputs!$C$3,"") -> 12.16558 | E5: =IFERROR((SUMPRODUCT(DCF!$B$2:$F$2,1/(1+$A5)^DCF!$B$3:$F$3)+((DCF!$B$8*(1+E$1)/($A5-E$1))/(1+$A5)^5)-Inputs!$C$5+Inputs!$C$4)/Inputs!$C$3,"") -> 14.142499
A6: 0.12 | B6: =IFERROR((SUMPRODUCT(DCF!$B$2:$F$2,1/(1+$A6)^DCF!$B$3:$F$3)+((DCF!$B$8*(1+B$1)/($A6-B$1))/(1+$A6)^5)-Inputs!$C$5+Inputs!$C$4)/Inputs!$C$3,"") -> 6.7131844 | C6: =IFERROR((SUMPRODUCT(DCF!$B$2:$F$2,1/(1+$A6)^DCF!$B$3:$F$3)+((DCF!$B$8*(1+C$1)/($A6-C$1))/(1+$A6)^5)-Inputs!$C$5+Inputs!$C$4)/Inputs!$C$3,"") -> 8.1279623 | D6: =IFERROR((SUMPRODUCT(DCF!$B$2:$F$2,1/(1+$A6)^DCF!$B$3:$F$3)+((DCF!$B$8*(1+D$1)/($A6-D$1))/(1+$A6)^5)-Inputs!$C$5+Inputs!$C$4)/Inputs!$C$3,"") -> 9.6916642 | E6: =IFERROR((SUMPRODUCT(DCF!$B$2:$F$2,1/(1+$A6)^DCF!$B$3:$F$3)+((DCF!$B$8*(1+E$1)/($A6-E$1))/(1+$A6)^5)-Inputs!$C$5+Inputs!$C$4)/Inputs!$C$3,"") -> 11.429111

Sheet Conclusion
A1: Investment Conclusion
A2: Based on the completed valuation work, I estimate Carriage Services’ fair value at approximately $24 to $32 per share, with a weighted valuation estimate of approximately $27 per share. The valuation is based primarily on normalized earnings and EBITDA multiples, while the DCF serves as a conservative downside check due to the company’s meaningful debt load. The dividend model is not a primary valuation method because the current dividend represents only a small portion of total owner earnings. At the current share price of approximately $44, CSV does not offer a sufficient margin of safety. The company’s leverage materially reduces the value attributable to common shareholders, and I am not assuming aggressive debt paydown without stronger evidence from management behavior. Applying a 15% margin of safety to the weighted value produces a target entry price of approximately $23 per share. CSV should remain on the watchlist, but I would not buy at the current price.
A5: Valuation Summary
A7: Method | B7: Estimated Value
A8: DCF | B8: =DCF!B18 -> 12.918058
A9: Dividend Model (Not Meaningful) | B9: ='Dividend Model'!C6 -> 5.79375
A10: Multiples Check | B10: ='Multiples Check'!D22 -> 31.597512
A11: Final Range | B11: =TEXT(ROUND(D21*0.9,0),"$0.00")&" - "&TEXT(ROUND(D21*1.2,0),"$0.00") -> $24.00 - $32.00
A13: Current Share Price | B13: =Inputs!C2 -> 44.07
A14: Implied Upside / Downside | B14: =D21/B13-1 -> -0.38898007
A15: Decision | B15: Watchlist / Do Not Buy
A17: Valuation Weighting | B17: Value | C17: Weight | D17: Weighted Value
A18: DCF | B18: =B8 -> 12.918058 | C18: 0.25 | D18: =B18*C18 -> 3.2295145
A19: Dividend Model | B19: =B9 -> 5.79375 | C19: 0 | D19: =B19*C19 -> 0
A20: Multiples Check | B20: =B10 -> 31.597512 | C20: 0.75 | D20: =B20*C20 -> 23.698134
A21: Weighted Value | D21: =SUM(D18:D20) -> 26.927648

Sheet Sources
A1: Data | B1: Source | C1: Link | D1: Notes
A2: Historical Financials | B2: sec.gov | C2: LINK
A3: Share Price | B3: finance.yahoo.com | C3: LINK
